pyaidrone/__init__.py
pyaidrone/aiDrone.py
pyaidrone/deflib.py
pyaidrone/edu.py
pyaidrone/ikeyevent.py
pyaidrone/packet.py
pyaidrone/parse.py
pyaidrone/sensor.py
pyaidrone/vision_ai.py
pyaidrone-1.19.dist-info/METADATA
pyaidrone-1.19.dist-info/WHEEL
pyaidrone-1.19.dist-info/top_level.txt
pyaidrone-1.19.dist-info/RECORD
