Metadata-Version: 2.1
Name: pyaidrone
Version: 1.19
Summary: Library for AIDrone Products
Home-page: http://www.ir-brain.com
Author: IR-Brain
Author-email: ceo@ir-brain.com
Classifier: Programming Language :: Python :: 3
Classifier: License :: OSI Approved :: MIT License
Classifier: Operating System :: OS Independent
Requires-Python: >=3.6
Requires-Dist: pyserial (>=3.4)
Requires-Dist: pynput (>=1.7.3)
